hurix_ai/__init__.py
hurix_ai/factchecker.py
hurix_ai-2.2.0.dist-info/METADATA
hurix_ai-2.2.0.dist-info/WHEEL
hurix_ai-2.2.0.dist-info/RECORD
